Asad_Stack/__init__.py
Asad_Stack/app.py
Asad_Stack/middleware.py
Asad_Stack/response.py
AsadStack-0.1.2.dist-info/METADATA
AsadStack-0.1.2.dist-info/WHEEL
AsadStack-0.1.2.dist-info/top_level.txt
AsadStack-0.1.2.dist-info/RECORD
